WinIDS/__init__.py
WinIDS/attack_panel.py
WinIDS/bridge.py
WinIDS/fast_run.py
WinIDS/monitor.py
WinIDS/pro_dashboard.py
WinIDS/rl_agent.py
WinIDS/attack_simulator/README.md
WinIDS/attack_simulator/__init__.py
WinIDS/attack_simulator/base.py
WinIDS/attack_simulator/dos.py
WinIDS/attack_simulator/probe.py
WinIDS/attack_simulator/r2l.py
WinIDS/attack_simulator/u2r.py
WinIDS/data/README.md
WinIDS/models/README.md
WinIDS/scripts/__init__.py
WinIDS/scripts/train_model.py
winids-0.1.1.dist-info/LICENSE
winids-0.1.1.dist-info/METADATA
winids-0.1.1.dist-info/WHEEL
winids-0.1.1.dist-info/entry_points.txt
winids-0.1.1.dist-info/top_level.txt
winids-0.1.1.dist-info/RECORD
