Metadata-Version: 2.1
Name: WinIDS
Version: 0.1.1
Summary: Windows-based Intrusion Detection System using machine learning and reinforcement learning for adaptive security
Home-page: https://github.com/Nandhan-KA/WinIDS
Author: Nandhan K
Author-email: developer.nandhank@gmail.com
Classifier: Programming Language :: Python :: 3
Classifier: License :: OSI Approved :: MIT License
Classifier: Operating System :: Microsoft :: Windows
Classifier: Topic :: Security
Classifier: Topic :: System :: Networking :: Monitoring
Classifier: Topic :: Scientific/Engineering :: Artificial Intelligence
Requires-Python: >=3.7
License-File: LICENSE
Requires-Dist: tensorflow >=2.0.0
Requires-Dist: numpy >=1.18.0
Requires-Dist: pandas >=1.0.0
Requires-Dist: matplotlib >=3.1.0
Requires-Dist: scikit-learn >=0.22.0
Requires-Dist: pillow >=7.0.0
